{
    "imagePath": "../Mammals.xcassets/BatEaredFox/Photos/BatEaredFoxTrans01.imageset/BatEaredFoxTrans01.png", 
    "imageData": "", 
    "shapes": [
        {
            "shape_type": "rectangle", 
            "points": [
                [
                    66.16541353383458, 
                    13.939849624060145
                ], 
                [
                    259.3984962406015, 
                    188.37593984962405
                ]
            ], 
            "flags": {}, 
            "group_id": null, 
            "label": "Face"
        }
    ], 
    "version": "4.5.9", 
    "flags": {}, 
    "imageHeight": 399, 
    "imageWidth": 600
}