{
    "imagePath": "../Mammals.xcassets/Gemsbok/Photos/Gemsbok09.imageset/Gemsbok09.png", 
    "imageData": "", 
    "shapes": [
        {
            "shape_type": "rectangle", 
            "points": [
                [
                    162.406015037594, 
                    37.75187969924812
                ], 
                [
                    493.98496240601503, 
                    376.09774436090225
                ]
            ], 
            "flags": {}, 
            "group_id": null, 
            "label": "CA"
        }
    ], 
    "version": "4.5.9", 
    "flags": {}, 
    "imageHeight": 397, 
    "imageWidth": 600
}